MNAnalyse
