Metadata-Version: 1.2
Name: MNAnalyse
Version: 0.0.6
Summary: Mouse Neuron Analyse
Home-page: https://gitee.com/usstc206/mnanalyse.git
Author: xfwang
Author-email: xfwang@ion.ac.cn
Maintainer: xfwang
Maintainer-email: xfwang@ion.ac.cn
License: BSD License
Platform: all
Classifier: Development Status :: 4 - Beta
Classifier: Operating System :: OS Independent
Classifier: Intended Audience :: Developers
Classifier: License :: OSI Approved :: BSD License
Classifier: Programming Language :: Python
Classifier: Programming Language :: Python :: Implementation
Classifier: Programming Language :: Python :: 2
Classifier: Programming Language :: Python :: 2.7
Classifier: Programming Language :: Python :: 3
Classifier: Programming Language :: Python :: 3.4
Classifier: Programming Language :: Python :: 3.5
Classifier: Programming Language :: Python :: 3.6
Classifier: Topic :: Software Development :: Libraries
